README.md
setup.py
qcloud_ccs/__init__.py
qcloud_ccs/api.py
qcloud_ccs/base.py
qcloud_ccs/log.py
qcloud_ccs/test.py
qcloud_ccs.egg-info/PKG-INFO
qcloud_ccs.egg-info/SOURCES.txt
qcloud_ccs.egg-info/dependency_links.txt
qcloud_ccs.egg-info/entry_points.txt
qcloud_ccs.egg-info/requires.txt
qcloud_ccs.egg-info/top_level.txt