Metadata-Version: 1.1
Name: qcloud-ccs
Version: 2.0.1
Summary: 以qcloud 容器服务sdk为基础. 1, 将机器创建/服务启停及更新等封装为接口;2.将机器和服务配置抽离为配置文件
Home-page: https://newops.cn/15077893526985.html
Author: wanglin
Author-email: wanglin@dbca.cn
License: GPLv2
Platform: UNKNOWN
Classifier: Programming Language :: Python
Classifier: Programming Language :: Python :: 3.6
